dependency_track_api/__init__.py
dependency_track_api/access_control_list.py
dependency_track_api/analysis.py
dependency_track_api/exceptions.py
dependency_track_api/session.py
dependency_track_api-0.1.5.dist-info/LICENSE
dependency_track_api-0.1.5.dist-info/METADATA
dependency_track_api-0.1.5.dist-info/WHEEL
dependency_track_api-0.1.5.dist-info/RECORD
