Metadata-Version: 2.3
Name: dependency-track-api
Version: 0.1.5
Summary: A wrapper for the Dependency Track REST API.
Author: MarcosRigal
Author-email: riveragavilanmarcos@gmail.com
Requires-Python: >=3.10,<=3.14
Classifier: Programming Language :: Python :: 3
Classifier: Programming Language :: Python :: 3.10
Classifier: Programming Language :: Python :: 3.11
Classifier: Programming Language :: Python :: 3.12
Classifier: Programming Language :: Python :: 3.13
Provides-Extra: tox-lint
Provides-Extra: tox-test
Requires-Dist: coverage[toml] (>=7.0,<8.0) ; extra == "tox-lint" or extra == "tox-test"
Requires-Dist: flake8 (==3.8.4) ; extra == "tox-lint" or extra == "tox-test"
Requires-Dist: flake8-eradicate (==1.1.0) ; extra == "tox-lint" or extra == "tox-test"
Requires-Dist: mypy (==0.910) ; extra == "tox-lint" or extra == "tox-test"
Requires-Dist: pylama (==7.7.1) ; extra == "tox-lint" or extra == "tox-test"
Requires-Dist: pylint (==2.6.0) ; extra == "tox-lint" or extra == "tox-test"
Requires-Dist: pylint-pytest (>=1.1.7,<2.0.0) ; extra == "tox-lint" or extra == "tox-test"
Requires-Dist: pytest (>=7.4,<8.0) ; extra == "tox-lint" or extra == "tox-test"
Requires-Dist: pytest-cov (==4.0.0) ; extra == "tox-lint" or extra == "tox-test"
Requires-Dist: pytest-emoji (==0.2.0) ; extra == "tox-lint" or extra == "tox-test"
Requires-Dist: pytest-mock (==3.10.0)
Requires-Dist: pytest-timeout (==2.1.0) ; extra == "tox-lint" or extra == "tox-test"
Requires-Dist: requests (>=2.31.0,<3.0.0)
Requires-Dist: requests-mock (>=1.12.1,<2.0.0)
Requires-Dist: tomli
Requires-Dist: types-requests (>=2.31.0.20240311,<3.0.0.0) ; extra == "tox-lint" or extra == "tox-test"
